LICENSE.txt
MANIFEST.in
setup.cfg
setup.py
redlock/__init__.py
redlock/cli.py
redlock/fifo.py
redlockfifo.egg-info/PKG-INFO
redlockfifo.egg-info/SOURCES.txt
redlockfifo.egg-info/dependency_links.txt
redlockfifo.egg-info/entry_points.txt
redlockfifo.egg-info/requires.txt
redlockfifo.egg-info/top_level.txt
tests/test_redlock.py
tests/test_redlock_fifo.py