Metadata-Version: 1.1
Name: redlockfifo
Version: 0.0.1
Summary: Redis locking mechanism
Home-page: https://github.com/mat128/redlock-py
Author: pjdecoursey@spscommerce.com
Author-email: webapps@spscommerce.com
License: UNKNOWN
Platform: UNKNOWN
Classifier: Development Status :: 5 - Production/Stable
Classifier: Intended Audience :: Developers
Classifier: License :: OSI Approved :: MIT License
Classifier: Programming Language :: Python :: 2.6
Classifier: Programming Language :: Python :: 2.7
Classifier: Programming Language :: Python :: 3
Classifier: Programming Language :: Python :: 3.2
Classifier: Programming Language :: Python :: 3.3
Classifier: Programming Language :: Python :: 3.4
